httpaws/__init__.py
httpaws/__main__.py
httpaws/core.py
httpaws-0.0.4.dist-info/LICENSE
httpaws-0.0.4.dist-info/METADATA
httpaws-0.0.4.dist-info/WHEEL
httpaws-0.0.4.dist-info/entry_points.txt
httpaws-0.0.4.dist-info/top_level.txt
httpaws-0.0.4.dist-info/RECORD
