Metadata-Version: 2.1
Name: httpaws
Version: 0.0.4
Summary: httpAWS - a CLI, cURL-like tool for AWS services.
Home-page: https://github.com/http-aws/http-aws
Author: Todd Leonhardt
Author-email: todd.leonhardt@gmail.com
License: Apache 2.0
Download-URL: https://github.com/http-aws/http-aws
Keywords: http cli aws
Platform: any
Classifier: Development Status :: 3 - Alpha
Classifier: Programming Language :: Python
Classifier: Programming Language :: Python :: 2.7
Classifier: Programming Language :: Python :: 3
Classifier: Programming Language :: Python :: 3.4
Classifier: Programming Language :: Python :: 3.5
Classifier: Programming Language :: Python :: 3.6
Classifier: Programming Language :: Python :: 3.7
Classifier: Environment :: Console
Classifier: Intended Audience :: Developers
Classifier: Intended Audience :: System Administrators
Classifier: License :: OSI Approved :: Apache Software License
Classifier: Topic :: Internet :: WWW/HTTP
Classifier: Topic :: Software Development
Classifier: Topic :: System :: Networking
Classifier: Topic :: Terminals
Classifier: Topic :: Text Processing
Classifier: Topic :: Utilities
Requires-Python: >=2.7
Requires-Dist: requests (>=2.19.0)
Requires-Dist: aws-requests-auth (>=0.4.0)
Requires-Dist: botocore (>=1.12.0)
Requires-Dist: colorama (>=0.3.0)
Requires-Dist: pygments (>=2.3.0)
Requires-Dist: lxml (>=4.0.0)
